pykafka/__init__.py
pykafka/balancedconsumer.py
pykafka/broker.py
pykafka/client.py
pykafka/cluster.py
pykafka/common.py
pykafka/connection.py
pykafka/exceptions.py
pykafka/handlers.py
pykafka/partition.py
pykafka/partitioners.py
pykafka/producer.py
pykafka/protocol.py
pykafka/simpleconsumer.py
pykafka/topic.py
pykafka/cli/__init__.py
pykafka/cli/kafka_tools.py
pykafka/test/__init__.py
pykafka/test/kafka_instance.py
pykafka/test/utils.py
pykafka/utils/__init__.py
pykafka/utils/compat.py
pykafka/utils/compression.py
pykafka/utils/error_handlers.py
pykafka/utils/socket.py
pykafka/utils/struct_helpers.py
pykafka-2.0.0.dist-info/DESCRIPTION.rst
pykafka-2.0.0.dist-info/METADATA
pykafka-2.0.0.dist-info/RECORD
pykafka-2.0.0.dist-info/WHEEL
pykafka-2.0.0.dist-info/entry_points.txt
pykafka-2.0.0.dist-info/metadata.json
pykafka-2.0.0.dist-info/pbr.json
pykafka-2.0.0.dist-info/top_level.txt
tests/__init__.py
tests/conftest.py
tests/pykafka/__init__.py
tests/pykafka/test_balancedconsumer.py
tests/pykafka/test_cluster.py
tests/pykafka/test_partition.py
tests/pykafka/test_producer.py
tests/pykafka/test_protocol.py
tests/pykafka/test_simpleconsumer.py
tests/pykafka/utils/__init__.py
tests/pykafka/utils/test_compression.py
tests/pykafka/utils/test_struct_helpers.py
