Metadata-Version: 2.0
Name: pykafka
Version: 2.0.0
Summary: Full-Featured Pure-Python Kafka Client
Home-page: https://github.com/Parsely/pykafka
Author: Keith Bourgoin and Emmett Butler
Author-email: pykafka-user@googlegroups.com
License: Apache License 2.0
Keywords: apache kafka client driver
Platform: UNKNOWN
Classifier: Development Status :: 5 - Production/Stable
Classifier: Intended Audience :: Developers
Classifier: License :: OSI Approved :: Apache Software License
Classifier: Programming Language :: Python
Classifier: Programming Language :: Python :: 2
Classifier: Programming Language :: Python :: 2.7
Classifier: Programming Language :: Python :: 3
Classifier: Programming Language :: Python :: 3.4
Classifier: Topic :: Database
Classifier: Topic :: Database :: Front-Ends
Classifier: Topic :: Software Development :: Libraries :: Python Modules
Requires-Dist: kazoo
Requires-Dist: tabulate
Provides-Extra: all
Requires-Dist: kazoo; extra == 'all'
Requires-Dist: mock; extra == 'all'
Requires-Dist: pytest; extra == 'all'
Requires-Dist: pytest-cov; extra == 'all'
Requires-Dist: python-snappy; extra == 'all'
Requires-Dist: tabulate; extra == 'all'
Requires-Dist: unittest2; extra == 'all'
Provides-Extra: docs
Requires-Dist: mock; extra == 'docs'
Requires-Dist: pytest; extra == 'docs'
Requires-Dist: pytest-cov; extra == 'docs'
Requires-Dist: python-snappy; extra == 'docs'
Requires-Dist: sphinx; extra == 'docs'
Requires-Dist: unittest2; extra == 'docs'
Provides-Extra: lint
Requires-Dist: pep8; extra == 'lint'
Requires-Dist: pyflakes; extra == 'lint'
Provides-Extra: test
Requires-Dist: mock; extra == 'test'
Requires-Dist: pytest; extra == 'test'
Requires-Dist: pytest-cov; extra == 'test'
Requires-Dist: python-snappy; extra == 'test'
Requires-Dist: unittest2; extra == 'test'
